[
  {
    "rank": 1,
    "no": 27,
    "name": "曾侯乙编钟",
    "era": "战国早期·约前5世纪",
    "museum": "湖北省博物馆",
    "历史": 98.95,
    "稀缺": 97.55,
    "艺术": 98.85,
    "符号": 98.9,
    "加权总分": 98.6
  },
  {
    "rank": 2,
    "no": 3,
    "name": "后母戊鼎",
    "era": "商后期·武丁至祖甲时期（约前13世纪-前12世纪）",
    "museum": "中国国家博物馆",
    "历史": 98.95,
    "稀缺": 96.6,
    "艺术": 95.55,
    "符号": 99.0,
    "加权总分": 97.67
  },
  {
    "rank": 3,
    "no": 65,
    "name": "陆机《平复帖》卷",
    "era": "西晋·约3世纪（陆机261-303年）",
    "museum": "故宫博物院",
    "历史": 98.6,
    "稀缺": 98.15,
    "艺术": 96.3,
    "符号": 93.85,
    "加权总分": 97.52
  },
  {
    "rank": 4,
    "no": 97,
    "name": "张择端《清明上河图》卷",
    "era": "北宋·约12世纪初（张择端约1085-1145年）",
    "museum": "故宫博物院",
    "历史": 97.3,
    "稀缺": 94.75,
    "艺术": 99.0,
    "符号": 99.0,
    "加权总分": 97.26
  },
  {
    "rank": 5,
    "no": 66,
    "name": "王珣《伯远帖》卷",
    "era": "东晋·约4世纪末（王珣350-401年）",
    "museum": "故宫博物院",
    "历史": 97.4,
    "稀缺": 98.7,
    "艺术": 96.0,
    "符号": 93.3,
    "加权总分": 96.98
  },
  {
    "rank": 6,
    "no": 67,
    "name": "冯承素摹王羲之《兰亭序》卷",
    "era": "唐·贞观年间（约7世纪中叶）",
    "museum": "故宫博物院",
    "历史": 96.8,
    "稀缺": 96.05,
    "艺术": 97.45,
    "符号": 97.9,
    "加权总分": 96.88
  },
  {
    "rank": 7,
    "no": 33,
    "name": "青铜神树",
    "era": "商晚期（约前13世纪-前12世纪）",
    "museum": "三星堆博物馆",
    "历史": 96.65,
    "稀缺": 97.15,
    "艺术": 96.3,
    "符号": 98.15,
    "加权总分": 96.84
  },
  {
    "rank": 8,
    "no": 37,
    "name": "铜车马",
    "era": "秦（前221-前206年）",
    "museum": "秦始皇帝陵博物院",
    "历史": 96.3,
    "稀缺": 95.95,
    "艺术": 96.55,
    "符号": 96.9,
    "加权总分": 96.33
  },
  {
    "rank": 9,
    "no": 106,
    "name": "铜立人像",
    "era": "商后期·约前13世纪-前12世纪",
    "museum": "三星堆博物馆",
    "历史": 95.6,
    "稀缺": 97.5,
    "艺术": 95.7,
    "符号": 96.8,
    "加权总分": 96.18
  },
  {
    "rank": 10,
    "no": 179,
    "name": "石鼓（1组10只）",
    "era": "战国·秦·约前4世纪-前3世纪",
    "museum": "故宫博物院",
    "历史": 97.5,
    "稀缺": 96.2,
    "艺术": 94.05,
    "符号": 93.25,
    "加权总分": 96.02
  },
  {
    "rank": 11,
    "no": 82,
    "name": "展子虔《游春图》卷",
    "era": "隋·约6世纪末-7世纪初（展子虔约550-604年）",
    "museum": "故宫博物院",
    "历史": 97.35,
    "稀缺": 95.15,
    "艺术": 95.8,
    "符号": 92.1,
    "加权总分": 95.98
  },
  {
    "rank": 12,
    "no": 40,
    "name": "何尊",
    "era": "西周早期·成王五年（约前11世纪）",
    "museum": "宝鸡青铜器博物院",
    "历史": 98.9,
    "稀缺": 95.35,
    "艺术": 88.35,
    "符号": 98.45,
    "加权总分": 95.72
  },
  {
    "rank": 13,
    "no": 98,
    "name": "王希孟《千里江山图》卷",
    "era": "北宋·政和三年（1113年，王希孟约1096-1115年）",
    "museum": "故宫博物院",
    "历史": 94.2,
    "稀缺": 94.15,
    "艺术": 98.75,
    "符号": 97.35,
    "加权总分": 95.5
  },
  {
    "rank": 14,
    "no": 59,
    "name": "马王堆一号墓T型帛画",
    "era": "西汉·约前2世纪",
    "museum": "湖南博物院",
    "历史": 95.8,
    "稀缺": 92.95,
    "艺术": 96.35,
    "符号": 95.65,
    "加权总分": 95.25
  },
  {
    "rank": 15,
    "no": 83,
    "name": "韩滉《五牛图》卷",
    "era": "唐·约8世纪（韩滉723-787年）",
    "museum": "故宫博物院",
    "历史": 95.3,
    "稀缺": 93.75,
    "艺术": 97.4,
    "符号": 93.05,
    "加权总分": 95.18
  },
  {
    "rank": 16,
    "no": 14,
    "name": "良渚出土玉琮王",
    "era": "新石器时代·良渚文化（约前3300-前2300年）",
    "museum": "浙江省博物馆",
    "历史": 95.7,
    "稀缺": 96.1,
    "艺术": 94.75,
    "符号": 91.65,
    "加权总分": 95.18
  },
  {
    "rank": 17,
    "no": 89,
    "name": "顾闳中《韩熙载夜宴图》卷",
    "era": "五代·南唐·约10世纪中叶（顾闳中约910-980年）",
    "museum": "故宫博物院",
    "历史": 94.5,
    "稀缺": 93.15,
    "艺术": 98.6,
    "符号": 95.25,
    "加权总分": 95.17
  },
  {
    "rank": 18,
    "no": 29,
    "name": "曾侯乙青铜尊盘",
    "era": "战国早期·约前5世纪",
    "museum": "湖北省博物馆",
    "历史": 94.7,
    "稀缺": 94.45,
    "艺术": 98.8,
    "符号": 89.75,
    "加权总分": 95.05
  },
  {
    "rank": 19,
    "no": 112,
    "name": "越王勾践剑",
    "era": "春秋晚期·约前5世纪",
    "museum": "湖北省博物馆",
    "历史": 94.1,
    "稀缺": 94.1,
    "艺术": 96.25,
    "符号": 98.5,
    "加权总分": 95.01
  },
  {
    "rank": 20,
    "no": 103,
    "name": "四羊方尊",
    "era": "商后期·约前13世纪-前12世纪",
    "museum": "中国国家博物馆",
    "历史": 94.65,
    "稀缺": 92.55,
    "艺术": 97.25,
    "符号": 95.7,
    "加权总分": 94.84
  },
  {
    "rank": 21,
    "no": 57,
    "name": "直裾素纱禅衣",
    "era": "西汉·约前2世纪",
    "museum": "湖南博物院",
    "历史": 92.9,
    "稀缺": 96.5,
    "艺术": 97.5,
    "符号": 93.25,
    "加权总分": 94.78
  },
  {
    "rank": 22,
    "no": 5,
    "name": "大盂鼎",
    "era": "西周·康王二十三年（约前10世纪）",
    "museum": "上海博物馆",
    "历史": 98.15,
    "稀缺": 92.25,
    "艺术": 90.5,
    "符号": 92.2,
    "加权总分": 94.52
  },
  {
    "rank": 23,
    "no": 4,
    "name": "利簋",
    "era": "西周早期·武王时期（约前1046年）",
    "museum": "中国国家博物馆",
    "历史": 98.85,
    "稀缺": 95.65,
    "艺术": 84.75,
    "符号": 93.6,
    "加权总分": 94.49
  },
  {
    "rank": 24,
    "no": 16,
    "name": "淅川出土铜禁",
    "era": "春秋中期·楚庄王时期（约前6世纪）",
    "museum": "河南博物院",
    "历史": 94.75,
    "稀缺": 96.4,
    "艺术": 96.15,
    "符号": 84.35,
    "加权总分": 94.4
  },
  {
    "rank": 25,
    "no": 159,
    "name": "太阳神鸟金箔片",
    "era": "商·约前12世纪-前11世纪",
    "museum": "成都金沙遗址博物馆",
    "历史": 92.6,
    "稀缺": 95.9,
    "艺术": 94.35,
    "符号": 98.95,
    "加权总分": 94.38
  },
  {
    "rank": 26,
    "no": 142,
    "name": "汝窑天青釉弦纹樽",
    "era": "北宋·约11世纪-12世纪初",
    "museum": "故宫博物院",
    "历史": 91.1,
    "稀缺": 98.25,
    "艺术": 97.2,
    "符号": 92.15,
    "加权总分": 94.19
  },
  {
    "rank": 27,
    "no": 10,
    "name": "大克鼎",
    "era": "西周·孝王时期（约前10世纪-前9世纪）",
    "museum": "上海博物馆",
    "历史": 95.5,
    "稀缺": 91.75,
    "艺术": 95.05,
    "符号": 91.9,
    "加权总分": 94.18
  },
  {
    "rank": 28,
    "no": 155,
    "name": "'皇后之玺'玉玺",
    "era": "西汉·约前2世纪",
    "museum": "陕西历史博物馆",
    "历史": 94.05,
    "稀缺": 98.7,
    "艺术": 90.5,
    "符号": 92.05,
    "加权总分": 94.14
  },
  {
    "rank": 29,
    "no": 28,
    "name": "曾侯乙墓外棺",
    "era": "战国早期·约前5世纪",
    "museum": "湖北省博物馆",
    "历史": 94.85,
    "稀缺": 94.2,
    "艺术": 95.25,
    "符号": 86.9,
    "加权总分": 93.99
  },
  {
    "rank": 30,
    "no": 9,
    "name": "晋侯苏钟（一套16件）",
    "era": "西周·厉王三十三年（前846年）",
    "museum": "上海博物馆/山西博物院",
    "历史": 98.1,
    "稀缺": 95.75,
    "艺术": 86.85,
    "符号": 84.3,
    "加权总分": 93.7
  },
  {
    "rank": 31,
    "no": 8,
    "name": "嵌绿松石象牙杯",
    "era": "商后期·武丁时期（约前13世纪-前12世纪）",
    "museum": "中国社会科学院考古研究所",
    "历史": 93.4,
    "稀缺": 95.65,
    "艺术": 95.9,
    "符号": 85.5,
    "加权总分": 93.68
  },
  {
    "rank": 32,
    "no": 72,
    "name": "唐人《摹王羲之一门书翰》卷",
    "era": "唐·约7世纪",
    "museum": "辽宁省博物馆",
    "历史": 94.85,
    "稀缺": 94.7,
    "艺术": 93.0,
    "符号": 86.9,
    "加权总分": 93.61
  },
  {
    "rank": 33,
    "no": 148,
    "name": "青花萧何月下追韩信图梅瓶",
    "era": "元·约14世纪中叶",
    "museum": "南京市博物馆",
    "历史": 91.05,
    "稀缺": 94.8,
    "艺术": 97.4,
    "符号": 93.85,
    "加权总分": 93.59
  },
  {
    "rank": 34,
    "no": 36,
    "name": "铜奔马",
    "era": "东汉·约2世纪",
    "museum": "甘肃省博物馆",
    "历史": 91.1,
    "稀缺": 91.85,
    "艺术": 97.95,
    "符号": 98.95,
    "加权总分": 93.56
  },
  {
    "rank": 35,
    "no": 47,
    "name": "八重宝函",
    "era": "唐·约9世纪",
    "museum": "法门寺博物馆",
    "历史": 92.4,
    "稀缺": 94.55,
    "艺术": 96.15,
    "符号": 89.7,
    "加权总分": 93.45
  },
  {
    "rank": 36,
    "no": 70,
    "name": "怀素《苦笋帖》卷",
    "era": "唐·约8世纪（怀素737-799年）",
    "museum": "上海博物馆",
    "历史": 92.05,
    "稀缺": 95.95,
    "艺术": 96.85,
    "符号": 86.45,
    "加权总分": 93.44
  },
  {
    "rank": 37,
    "no": 42,
    "name": "大秦景教流行中国碑",
    "era": "唐·建中二年（781年）",
    "museum": "西安碑林博物馆",
    "历史": 97.55,
    "稀缺": 94.85,
    "艺术": 84.65,
    "符号": 90.4,
    "加权总分": 93.38
  },
  {
    "rank": 38,
    "no": 64,
    "name": "五星出东方护膊",
    "era": "东汉末-魏晋（约3世纪-4世纪）",
    "museum": "新疆维吾尔自治区博物馆",
    "历史": 93.35,
    "稀缺": 95.6,
    "艺术": 90.45,
    "符号": 94.8,
    "加权总分": 93.37
  },
  {
    "rank": 39,
    "no": 51,
    "name": "刘胜金缕玉衣",
    "era": "西汉·约前113年",
    "museum": "河北博物院",
    "历史": 93.8,
    "稀缺": 93.15,
    "艺术": 92.3,
    "符号": 94.05,
    "加权总分": 93.35
  },
  {
    "rank": 40,
    "no": 160,
    "name": "金杖",
    "era": "商·约前13世纪-前12世纪",
    "museum": "三星堆博物馆",
    "历史": 94.5,
    "稀缺": 94.75,
    "艺术": 88.5,
    "符号": 95.3,
    "加权总分": 93.32
  },
  {
    "rank": 41,
    "no": 180,
    "name": "昭陵六骏石刻（什伐赤、白蹄乌、特勒骠、青骓4幅）",
    "era": "唐·贞观年间（约7世纪）",
    "museum": "西安碑林博物馆",
    "历史": 94.3,
    "稀缺": 88.2,
    "艺术": 97.1,
    "符号": 92.3,
    "加权总分": 93.31
  },
  {
    "rank": 42,
    "no": 111,
    "name": "逨盘",
    "era": "西周·约前9世纪-前8世纪",
    "museum": "宝鸡青铜器博物院",
    "历史": 97.65,
    "稀缺": 94.3,
    "艺术": 87.75,
    "符号": 82.85,
    "加权总分": 93.22
  },
  {
    "rank": 43,
    "no": 52,
    "name": "长信宫灯",
    "era": "西汉·约前2世纪",
    "museum": "河北博物院",
    "历史": 91.55,
    "稀缺": 92.1,
    "艺术": 96.05,
    "符号": 96.2,
    "加权总分": 93.13
  },
  {
    "rank": 44,
    "no": 150,
    "name": "红山文化玉龙",
    "era": "新石器时代·红山文化（约前4000-前3000年）",
    "museum": "中国国家博物馆",
    "历史": 94.7,
    "稀缺": 92.9,
    "艺术": 88.85,
    "符号": 95.9,
    "加权总分": 93.12
  },
  {
    "rank": 45,
    "no": 68,
    "name": "欧阳询《梦奠帖》卷",
    "era": "唐·约7世纪初（欧阳询557-641年）",
    "museum": "辽宁省博物馆",
    "历史": 92.45,
    "稀缺": 94.5,
    "艺术": 96.0,
    "符号": 86.3,
    "加权总分": 93.09
  },
  {
    "rank": 46,
    "no": 56,
    "name": "人物龙凤帛画",
    "era": "战国·约前4世纪-前3世纪",
    "museum": "湖南省博物馆",
    "历史": 94.85,
    "稀缺": 93.6,
    "艺术": 90.25,
    "符号": 88.65,
    "加权总分": 92.93
  },
  {
    "rank": 47,
    "no": 71,
    "name": "杜牧《张好好诗》卷",
    "era": "唐·大和九年（835年，杜牧约803-852年）",
    "museum": "故宫博物院",
    "历史": 92.45,
    "稀缺": 95.6,
    "艺术": 94.4,
    "符号": 85.1,
    "加权总分": 92.87
  },
  {
    "rank": 48,
    "no": 81,
    "name": "赵佶《草书千字文》卷",
    "era": "北宋·政和年间（约1111-1118年，赵佶1082-1135年）",
    "museum": "辽宁省博物馆",
    "历史": 91.2,
    "稀缺": 92.15,
    "艺术": 97.65,
    "符号": 89.6,
    "加权总分": 92.68
  },
  {
    "rank": 49,
    "no": 191,
    "name": "郭店楚简《老子（甲、乙、丙）》",
    "era": "战国中期·约前4世纪",
    "museum": "荆门市博物馆",
    "历史": 97.95,
    "稀缺": 96.6,
    "艺术": 79.7,
    "符号": 88.05,
    "加权总分": 92.63
  },
  {
    "rank": 50,
    "no": 154,
    "name": "多节活环套练玉佩",
    "era": "战国早期·约前5世纪",
    "museum": "湖北省博物馆",
    "历史": 90.35,
    "稀缺": 95.25,
    "艺术": 98.15,
    "符号": 83.35,
    "加权总分": 92.49
  },
  {
    "rank": 51,
    "no": 115,
    "name": "诅盟场面贮贝器",
    "era": "西汉·约前2世纪",
    "museum": "中国国家博物馆",
    "历史": 94.45,
    "稀缺": 91.95,
    "艺术": 92.0,
    "符号": 85.65,
    "加权总分": 92.46
  },
  {
    "rank": 52,
    "no": 6,
    "name": "虢季子白盘",
    "era": "西周·宣王十二年（前816年）",
    "museum": "中国国家博物馆",
    "历史": 95.1,
    "稀缺": 92.85,
    "艺术": 89.25,
    "符号": 86.3,
    "加权总分": 92.42
  },
  {
    "rank": 53,
    "no": 109,
    "name": "晋侯鸟尊",
    "era": "西周·约前10世纪-前9世纪",
    "museum": "山西博物院",
    "历史": 91.7,
    "稀缺": 90.6,
    "艺术": 95.15,
    "符号": 91.05,
    "加权总分": 92.14
  },
  {
    "rank": 54,
    "no": 31,
    "name": "红山文化女神像",
    "era": "新石器时代晚期·红山文化（约前4000-前3000年）",
    "museum": "辽宁省博物馆",
    "历史": 93.7,
    "稀缺": 95.3,
    "艺术": 86.6,
    "符号": 89.75,
    "加权总分": 92.11
  },
  {
    "rank": 55,
    "no": 102,
    "name": "子龙鼎",
    "era": "商后期·约前13世纪-前12世纪",
    "museum": "中国国家博物馆",
    "历史": 92.7,
    "稀缺": 94.25,
    "艺术": 91.05,
    "符号": 86.75,
    "加权总分": 92.1
  },
  {
    "rank": 56,
    "no": 80,
    "name": "米芾《苕溪诗》卷",
    "era": "北宋·元祐三年（1088年，米芾1051-1107年）",
    "museum": "故宫博物院",
    "历史": 90.45,
    "稀缺": 91.55,
    "艺术": 97.5,
    "符号": 88.35,
    "加权总分": 92.04
  },
  {
    "rank": 57,
    "no": 46,
    "name": "银花双轮十二环锡杖",
    "era": "唐·咸通十四年（873年）",
    "museum": "法门寺博物馆",
    "历史": 91.0,
    "稀缺": 95.3,
    "艺术": 93.95,
    "符号": 84.95,
    "加权总分": 92.03
  },
  {
    "rank": 58,
    "no": 49,
    "name": "铜错金银四龙四凤方案",
    "era": "战国·约前4世纪",
    "museum": "河北博物院",
    "历史": 90.95,
    "稀缺": 91.35,
    "艺术": 97.5,
    "符号": 85.9,
    "加权总分": 91.98
  },
  {
    "rank": 59,
    "no": 7,
    "name": "凤冠（六龙三凤冠等）",
    "era": "明·万历年间（1573-1620年）",
    "museum": "中国国家博物馆/故宫博物院/明十三陵博物馆",
    "历史": 90.05,
    "稀缺": 90.75,
    "艺术": 96.8,
    "符号": 92.2,
    "加权总分": 91.91
  },
  {
    "rank": 60,
    "no": 17,
    "name": "新郑出土莲鹤铜方壶",
    "era": "春秋中期·郑国（约前6世纪）",
    "museum": "故宫博物院",
    "历史": 92.2,
    "稀缺": 88.45,
    "艺术": 95.7,
    "符号": 90.0,
    "加权总分": 91.89
  },
  {
    "rank": 61,
    "no": 63,
    "name": "竹林七贤砖印模画",
    "era": "南朝·约5世纪-6世纪",
    "museum": "南京博物院",
    "历史": 93.45,
    "稀缺": 92.3,
    "艺术": 90.75,
    "符号": 86.1,
    "加权总分": 91.86
  },
  {
    "rank": 62,
    "no": 44,
    "name": "兽首玛瑙杯",
    "era": "唐·约8世纪",
    "museum": "陕西历史博物馆",
    "历史": 90.35,
    "稀缺": 92.0,
    "艺术": 96.05,
    "符号": 88.55,
    "加权总分": 91.8
  },
  {
    "rank": 63,
    "no": 2,
    "name": "陶鹰鼎",
    "era": "新石器时代·仰韶文化（约前5000-前3000年）",
    "museum": "中国国家博物馆",
    "历史": 91.15,
    "稀缺": 90.85,
    "艺术": 95.45,
    "符号": 88.75,
    "加权总分": 91.79
  },
  {
    "rank": 64,
    "no": 48,
    "name": "铜浮屠",
    "era": "唐·约9世纪",
    "museum": "法门寺博物馆",
    "历史": 92.25,
    "稀缺": 93.95,
    "艺术": 88.95,
    "符号": 88.0,
    "加权总分": 91.49
  },
  {
    "rank": 65,
    "no": 23,
    "name": "娄睿墓鞍马出行图壁画",
    "era": "北齐·武平元年（570年）",
    "museum": "山西博物院",
    "历史": 91.9,
    "稀缺": 90.5,
    "艺术": 95.65,
    "符号": 82.6,
    "加权总分": 91.47
  },
  {
    "rank": 66,
    "no": 41,
    "name": "茂陵石雕",
    "era": "西汉·武帝时期（约前2世纪）",
    "museum": "茂陵博物馆",
    "历史": 91.3,
    "稀缺": 88.3,
    "艺术": 95.35,
    "符号": 90.3,
    "加权总分": 91.4
  },
  {
    "rank": 67,
    "no": 1,
    "name": "彩绘鹳鱼石斧图陶缸",
    "era": "新石器时代·仰韶文化（约前5000-前3000年）",
    "museum": "中国国家博物馆",
    "历史": 92.9,
    "稀缺": 89.8,
    "艺术": 91.2,
    "符号": 88.1,
    "加权总分": 91.33
  },
  {
    "rank": 68,
    "no": 110,
    "name": "㝬簋",
    "era": "西周·厉王时期（约前9世纪）",
    "museum": "宝鸡青铜器博物院",
    "历史": 94.05,
    "稀缺": 91.95,
    "艺术": 88.65,
    "符号": 82.75,
    "加权总分": 91.25
  },
  {
    "rank": 69,
    "no": 149,
    "name": "蓝釉白龙纹梅瓶",
    "era": "元·约14世纪",
    "museum": "扬州博物馆",
    "历史": 87.15,
    "稀缺": 96.4,
    "艺术": 95.05,
    "符号": 89.1,
    "加权总分": 91.21
  },
  {
    "rank": 70,
    "no": 50,
    "name": "中山王铁足铜鼎",
    "era": "战国·约前4世纪",
    "museum": "河北博物院",
    "历史": 94.9,
    "稀缺": 90.75,
    "艺术": 88.25,
    "符号": 81.75,
    "加权总分": 91.17
  },
  {
    "rank": 71,
    "no": 117,
    "name": "杀人祭柱场面贮贝器",
    "era": "西汉·约前2世纪",
    "museum": "云南省博物馆",
    "历史": 91.65,
    "稀缺": 92.3,
    "艺术": 92.25,
    "符号": 83.15,
    "加权总分": 91.08
  },
  {
    "rank": 72,
    "no": 38,
    "name": "墙盘",
    "era": "西周中期·约前10世纪-前9世纪",
    "museum": "宝鸡青铜器博物院",
    "历史": 96.2,
    "稀缺": 90.0,
    "艺术": 86.25,
    "符号": 80.75,
    "加权总分": 91.04
  },
  {
    "rank": 73,
    "no": 151,
    "name": "良渚文化神人兽面纹玉钺",
    "era": "新石器时代·良渚文化（约前3300-前2300年）",
    "museum": "浙江省博物馆",
    "历史": 92.2,
    "稀缺": 89.95,
    "艺术": 92.6,
    "符号": 84.8,
    "加权总分": 91.03
  },
  {
    "rank": 74,
    "no": 158,
    "name": "'统领释教大元国师之印'龙钮玉印",
    "era": "元·约13世纪-14世纪",
    "museum": "西藏博物馆",
    "历史": 93.2,
    "稀缺": 91.6,
    "艺术": 85.8,
    "符号": 88.15,
    "加权总分": 90.7
  },
  {
    "rank": 75,
    "no": 11,
    "name": "太保鼎",
    "era": "西周·成王时期（约前11世纪-前10世纪）",
    "museum": "天津博物馆",
    "历史": 92.4,
    "稀缺": 92.15,
    "艺术": 88.3,
    "符号": 83.6,
    "加权总分": 90.56
  },
  {
    "rank": 76,
    "no": 43,
    "name": "舞马衔杯仿皮囊式银壶",
    "era": "唐·约8世纪",
    "museum": "陕西历史博物馆",
    "历史": 88.8,
    "稀缺": 90.3,
    "艺术": 94.8,
    "符号": 87.6,
    "加权总分": 90.34
  },
  {
    "rank": 77,
    "no": 79,
    "name": "黄庭坚《诸上座》卷",
    "era": "北宋·约11世纪末（黄庭坚1045-1105年）",
    "museum": "故宫博物院",
    "历史": 89.15,
    "稀缺": 89.15,
    "艺术": 96.6,
    "符号": 84.5,
    "加权总分": 90.32
  },
  {
    "rank": 78,
    "no": 19,
    "name": "铸客大铜鼎",
    "era": "战国晚期·楚国（约前3世纪）",
    "museum": "中国国家博物馆",
    "历史": 92.5,
    "稀缺": 89.85,
    "艺术": 88.3,
    "符号": 84.6,
    "加权总分": 90.18
  },
  {
    "rank": 79,
    "no": 190,
    "name": "战国简《金縢》",
    "era": "战国·约前4世纪-前3世纪",
    "museum": "清华大学",
    "历史": 96.35,
    "稀缺": 96.75,
    "艺术": 75.5,
    "符号": 79.4,
    "加权总分": 90.16
  },
  {
    "rank": 80,
    "no": 12,
    "name": "河姆渡出土朱漆碗",
    "era": "新石器时代·河姆渡文化（约前5000-前3300年）",
    "museum": "浙江省博物馆",
    "历史": 94.2,
    "稀缺": 94.75,
    "艺术": 81.05,
    "符号": 81.45,
    "加权总分": 90.16
  },
  {
    "rank": 81,
    "no": 118,
    "name": "仰韶文化彩陶人面鱼纹盆",
    "era": "新石器时代·仰韶文化（约前5000-前3000年）",
    "museum": "中国国家博物馆",
    "历史": 91.1,
    "稀缺": 87.4,
    "艺术": 88.8,
    "符号": 94.75,
    "加权总分": 90.11
  },
  {
    "rank": 82,
    "no": 92,
    "name": "黄筌《写生珍禽图》卷",
    "era": "五代·后蜀·约10世纪（黄筌约903-965年）",
    "museum": "故宫博物院",
    "历史": 88.85,
    "稀缺": 90.15,
    "艺术": 95.3,
    "符号": 83.75,
    "加权总分": 90.06
  },
  {
    "rank": 83,
    "no": 195,
    "name": "马王堆汉墓帛书《周易》",
    "era": "西汉·约前2世纪",
    "museum": "湖南省博物馆",
    "历史": 96.25,
    "稀缺": 93.05,
    "艺术": 77.25,
    "符号": 83.2,
    "加权总分": 90.03
  },
  {
    "rank": 84,
    "no": 162,
    "name": "'滇王之印'金印",
    "era": "西汉·元封二年（前109年）",
    "museum": "中国国家博物馆",
    "历史": 92.6,
    "稀缺": 93.05,
    "艺术": 82.0,
    "符号": 88.75,
    "加权总分": 89.99
  },
  {
    "rank": 85,
    "no": 113,
    "name": "商鞅方升",
    "era": "战国·秦孝公十八年（前344年）",
    "museum": "上海博物馆",
    "历史": 96.3,
    "稀缺": 91.6,
    "艺术": 77.05,
    "符号": 85.05,
    "加权总分": 89.86
  },
  {
    "rank": 86,
    "no": 145,
    "name": "定窑白釉刻莲花瓣纹龙首净瓶",
    "era": "北宋·约11世纪",
    "museum": "定州市博物馆",
    "历史": 87.4,
    "稀缺": 92.85,
    "艺术": 95.75,
    "符号": 81.0,
    "加权总分": 89.85
  },
  {
    "rank": 87,
    "no": 91,
    "name": "董源《山口待渡图》卷",
    "era": "五代·南唐·约10世纪（董源约943-962年）",
    "museum": "辽宁省博物馆",
    "历史": 89.75,
    "稀缺": 87.9,
    "艺术": 95.5,
    "符号": 81.9,
    "加权总分": 89.8
  },
  {
    "rank": 88,
    "no": 85,
    "name": "孙位《高逸图》卷",
    "era": "唐·约9世纪（孙位生卒年不详）",
    "museum": "上海博物馆",
    "历史": 88.8,
    "稀缺": 89.85,
    "艺术": 94.75,
    "符号": 82.5,
    "加权总分": 89.72
  },
  {
    "rank": 89,
    "no": 58,
    "name": "马王堆一号墓木棺椁",
    "era": "西汉·约前2世纪",
    "museum": "湖南博物院",
    "历史": 92.0,
    "稀缺": 87.8,
    "艺术": 90.3,
    "符号": 82.1,
    "加权总分": 89.67
  },
  {
    "rank": 90,
    "no": 107,
    "name": "天亡簋",
    "era": "西周早期·约前11世纪-前10世纪",
    "museum": "中国国家博物馆",
    "历史": 95.8,
    "稀缺": 90.05,
    "艺术": 80.6,
    "符号": 81.05,
    "加权总分": 89.66
  },
  {
    "rank": 91,
    "no": 105,
    "name": "大禾方鼎",
    "era": "商后期·约前13世纪-前12世纪",
    "museum": "湖南省博物馆",
    "历史": 89.85,
    "稀缺": 90.1,
    "艺术": 91.35,
    "符号": 84.05,
    "加权总分": 89.66
  },
  {
    "rank": 92,
    "no": 119,
    "name": "马家窑文化彩陶舞蹈纹盆",
    "era": "新石器时代·马家窑文化（约前3300-前2000年）",
    "museum": "中国国家博物馆",
    "历史": 90.25,
    "稀缺": 89.25,
    "艺术": 89.8,
    "符号": 86.65,
    "加权总分": 89.56
  },
  {
    "rank": 93,
    "no": 161,
    "name": "包金镶玉嵌琉璃银带钩",
    "era": "战国·约前4世纪-前3世纪",
    "museum": "中国国家博物馆",
    "历史": 87.55,
    "稀缺": 90.55,
    "艺术": 96.1,
    "符号": 81.7,
    "加权总分": 89.54
  },
  {
    "rank": 94,
    "no": 188,
    "name": "懿德太子墓壁画阙楼图（1组）",
    "era": "唐·神龙二年（706年）",
    "museum": "陕西历史博物馆",
    "历史": 89.95,
    "稀缺": 87.05,
    "艺术": 93.3,
    "符号": 82.4,
    "加权总分": 89.27
  },
  {
    "rank": 95,
    "no": 34,
    "name": "三星堆出土玉边璋",
    "era": "商晚期（约前13世纪-前12世纪）",
    "museum": "三星堆博物馆",
    "历史": 90.25,
    "稀缺": 91.5,
    "艺术": 86.4,
    "符号": 84.9,
    "加权总分": 89.16
  },
  {
    "rank": 96,
    "no": 134,
    "name": "陶骆驼载乐舞三彩俑",
    "era": "唐·约8世纪",
    "museum": "中国国家博物馆",
    "历史": 88.3,
    "稀缺": 86.95,
    "艺术": 93.15,
    "符号": 89.2,
    "加权总分": 89.15
  },
  {
    "rank": 97,
    "no": 22,
    "name": "司马金龙墓出土漆屏",
    "era": "北魏·太和八年（484年）",
    "museum": "山西博物院",
    "历史": 89.0,
    "稀缺": 91.65,
    "艺术": 92.15,
    "符号": 77.35,
    "加权总分": 89.14
  },
  {
    "rank": 98,
    "no": 54,
    "name": "角形玉杯",
    "era": "西汉·约前2世纪",
    "museum": "南越王博物院",
    "历史": 86.8,
    "稀缺": 91.4,
    "艺术": 94.8,
    "符号": 81.6,
    "加权总分": 89.1
  },
  {
    "rank": 99,
    "no": 187,
    "name": "章怀太子墓壁画狩猎出行图（1组）",
    "era": "唐·神龙二年（706年）",
    "museum": "陕西历史博物馆",
    "历史": 90.35,
    "稀缺": 87.1,
    "艺术": 91.65,
    "符号": 82.0,
    "加权总分": 89.05
  },
  {
    "rank": 100,
    "no": 84,
    "name": "周昉《挥扇仕女图》卷",
    "era": "唐·约8世纪-9世纪（周昉约730-800年）",
    "museum": "故宫博物院",
    "历史": 88.2,
    "稀缺": 87.8,
    "艺术": 94.0,
    "符号": 84.65,
    "加权总分": 89.03
  },
  {
    "rank": 101,
    "no": 122,
    "name": "龙山文化彩绘蟠龙纹陶盘",
    "era": "新石器时代·龙山文化（约前2500-前2000年）",
    "museum": "中国社会科学院考古研究所",
    "历史": 90.8,
    "稀缺": 89.45,
    "艺术": 85.3,
    "符号": 88.1,
    "加权总分": 89.01
  },
  {
    "rank": 102,
    "no": 192,
    "name": "楚简《孔子诗论》",
    "era": "战国·约前4世纪-前3世纪",
    "museum": "上海博物馆",
    "历史": 94.75,
    "稀缺": 93.2,
    "艺术": 77.75,
    "符号": 77.95,
    "加权总分": 88.97
  },
  {
    "rank": 103,
    "no": 61,
    "name": "西夏文佛经《吉祥遍至口和本续》纸本",
    "era": "西夏·约12世纪",
    "museum": "中国国家图书馆",
    "历史": 92.95,
    "稀缺": 95.7,
    "艺术": 77.4,
    "符号": 80.2,
    "加权总分": 88.89
  },
  {
    "rank": 104,
    "no": 62,
    "name": "青花釉里红瓷仓",
    "era": "元·约14世纪",
    "museum": "江西省博物馆",
    "历史": 87.45,
    "稀缺": 91.1,
    "艺术": 93.3,
    "符号": 79.95,
    "加权总分": 88.83
  },
  {
    "rank": 105,
    "no": 24,
    "name": "涅槃变相碑",
    "era": "唐·武周时期（约7世纪末-8世纪初）",
    "museum": "山西博物院",
    "历史": 89.85,
    "稀缺": 87.75,
    "艺术": 91.45,
    "符号": 80.55,
    "加权总分": 88.79
  },
  {
    "rank": 106,
    "no": 55,
    "name": "人物御龙帛画",
    "era": "战国·约前4世纪-前3世纪",
    "museum": "湖南省博物馆",
    "历史": 89.8,
    "稀缺": 90.5,
    "艺术": 87.85,
    "符号": 82.2,
    "加权总分": 88.77
  },
  {
    "rank": 107,
    "no": 176,
    "name": "刺绣佛像供养人",
    "era": "北魏·太和十一年（487年）",
    "museum": "敦煌研究院",
    "历史": 88.95,
    "稀缺": 92.9,
    "艺术": 88.55,
    "符号": 78.7,
    "加权总分": 88.75
  },
  {
    "rank": 108,
    "no": 138,
    "name": "三彩骆驼载乐俑",
    "era": "唐·约8世纪",
    "museum": "陕西历史博物馆",
    "历史": 87.9,
    "稀缺": 86.2,
    "艺术": 93.1,
    "符号": 88.4,
    "加权总分": 88.7
  },
  {
    "rank": 109,
    "no": 73,
    "name": "杨凝式《神仙起居法帖》卷",
    "era": "五代·后汉·乾祐元年（948年，杨凝式873-954年）",
    "museum": "故宫博物院",
    "历史": 87.6,
    "稀缺": 88.9,
    "艺术": 94.2,
    "符号": 80.35,
    "加权总分": 88.63
  },
  {
    "rank": 110,
    "no": 45,
    "name": "景云铜钟",
    "era": "唐·景云二年（711年）",
    "museum": "西安碑林博物馆",
    "历史": 87.65,
    "稀缺": 86.3,
    "艺术": 91.9,
    "符号": 90.6,
    "加权总分": 88.57
  },
  {
    "rank": 111,
    "no": 170,
    "name": "木雕真珠舍利宝幢（含木函）",
    "era": "北宋·大中祥符六年（1013年）",
    "museum": "苏州博物馆",
    "历史": 86.45,
    "稀缺": 90.0,
    "艺术": 94.75,
    "符号": 80.7,
    "加权总分": 88.52
  },
  {
    "rank": 112,
    "no": 26,
    "name": "大玉戈",
    "era": "商前期（约前16世纪-前14世纪）",
    "museum": "湖北省博物馆",
    "历史": 88.0,
    "稀缺": 93.0,
    "艺术": 88.5,
    "符号": 79.65,
    "加权总分": 88.42
  },
  {
    "rank": 113,
    "no": 87,
    "name": "周文矩《重屏会棋图》卷",
    "era": "五代·南唐·约10世纪（周文矩生卒年不详）",
    "museum": "故宫博物院",
    "历史": 88.1,
    "稀缺": 87.65,
    "艺术": 93.15,
    "符号": 81.25,
    "加权总分": 88.42
  },
  {
    "rank": 114,
    "no": 193,
    "name": "云梦睡虎地秦简《语书》",
    "era": "秦·约前3世纪",
    "museum": "湖北省博物馆",
    "历史": 95.1,
    "稀缺": 90.85,
    "艺术": 75.5,
    "符号": 81.15,
    "加权总分": 88.42
  },
  {
    "rank": 115,
    "no": 114,
    "name": "错金银镶嵌丝网套铜壶",
    "era": "战国·约前4世纪-前3世纪",
    "museum": "南京博物院",
    "历史": 87.0,
    "稀缺": 88.85,
    "艺术": 94.85,
    "符号": 79.35,
    "加权总分": 88.39
  },
  {
    "rank": 116,
    "no": 143,
    "name": "官窑弦纹瓶",
    "era": "北宋·约11世纪-12世纪初",
    "museum": "故宫博物院",
    "历史": 85.95,
    "稀缺": 89.6,
    "艺术": 94.55,
    "符号": 82.0,
    "加权总分": 88.29
  },
  {
    "rank": 117,
    "no": 75,
    "name": "蔡襄《自书诗》卷",
    "era": "北宋·皇祐年间（1049-1054年，蔡襄1012-1067年）",
    "museum": "故宫博物院",
    "历史": 86.65,
    "稀缺": 88.35,
    "艺术": 94.05,
    "符号": 82.1,
    "加权总分": 88.21
  },
  {
    "rank": 118,
    "no": 181,
    "name": "拓西岳华山庙碑册（华阴本）",
    "era": "宋·约11世纪-12世纪",
    "museum": "故宫博物院",
    "历史": 90.2,
    "稀缺": 93.6,
    "艺术": 84.05,
    "符号": 75.4,
    "加权总分": 88.15
  },
  {
    "rank": 119,
    "no": 21,
    "name": "朱然墓出土贵族生活图漆盘",
    "era": "三国·吴·赤乌年间（238-251年）",
    "museum": "马鞍山市三国朱然家族墓地博物馆",
    "历史": 89.1,
    "稀缺": 92.85,
    "艺术": 87.4,
    "符号": 74.55,
    "加权总分": 88.13
  },
  {
    "rank": 120,
    "no": 189,
    "name": "永泰公主墓壁画宫女图（1组）",
    "era": "唐·神龙二年（706年）",
    "museum": "陕西历史博物馆",
    "历史": 87.65,
    "稀缺": 86.5,
    "艺术": 93.0,
    "符号": 82.6,
    "加权总分": 88.06
  },
  {
    "rank": 121,
    "no": 30,
    "name": "彩漆木雕小座屏",
    "era": "战国·约前4世纪",
    "museum": "湖北省博物馆",
    "历史": 85.35,
    "稀缺": 89.55,
    "艺术": 95.8,
    "符号": 78.5,
    "加权总分": 87.93
  },
  {
    "rank": 122,
    "no": 39,
    "name": "淳化大鼎",
    "era": "西周·约前10世纪-前9世纪",
    "museum": "淳化县博物馆",
    "历史": 88.8,
    "稀缺": 91.9,
    "艺术": 86.2,
    "符号": 78.6,
    "加权总分": 87.92
  },
  {
    "rank": 123,
    "no": 15,
    "name": "水晶杯",
    "era": "战国晚期（约前4世纪-前3世纪）",
    "museum": "杭州博物馆",
    "历史": 84.4,
    "稀缺": 93.1,
    "艺术": 91.4,
    "符号": 83.9,
    "加权总分": 87.89
  },
  {
    "rank": 124,
    "no": 104,
    "name": "龙纹兕觥",
    "era": "商后期·约前13世纪-前12世纪",
    "museum": "山西博物院",
    "历史": 87.35,
    "稀缺": 88.95,
    "艺术": 90.9,
    "符号": 78.75,
    "加权总分": 87.64
  },
  {
    "rank": 125,
    "no": 129,
    "name": "青釉仰覆莲花尊",
    "era": "北齐·约6世纪",
    "museum": "中国国家博物馆",
    "历史": 87.1,
    "稀缺": 88.85,
    "艺术": 92.05,
    "符号": 77.4,
    "加权总分": 87.62
  },
  {
    "rank": 126,
    "no": 18,
    "name": "齐王墓青铜方镜",
    "era": "西汉早期（约前2世纪）",
    "museum": "淄博市博物馆",
    "历史": 86.35,
    "稀缺": 95.6,
    "艺术": 86.25,
    "符号": 77.8,
    "加权总分": 87.6
  },
  {
    "rank": 127,
    "no": 32,
    "name": "鸭形玻璃注",
    "era": "北燕·太平年间（409-430年）",
    "museum": "辽宁省博物馆",
    "历史": 85.75,
    "稀缺": 93.15,
    "艺术": 89.9,
    "符号": 74.9,
    "加权总分": 87.28
  },
  {
    "rank": 128,
    "no": 186,
    "name": "章怀太子墓壁画马球图（1组）",
    "era": "唐·神龙二年（706年）",
    "museum": "陕西历史博物馆",
    "历史": 88.7,
    "稀缺": 86.6,
    "艺术": 87.95,
    "符号": 80.6,
    "加权总分": 87.24
  },
  {
    "rank": 129,
    "no": 183,
    "name": "写本王仁煦《刊谬补缺切韵》",
    "era": "唐·约7世纪-8世纪",
    "museum": "故宫博物院",
    "历史": 93.25,
    "稀缺": 92.15,
    "艺术": 76.9,
    "符号": 71.5,
    "加权总分": 87.23
  },
  {
    "rank": 130,
    "no": 93,
    "name": "王诜《渔村小雪图》卷",
    "era": "北宋·约11世纪（王诜约1048-1104年）",
    "museum": "故宫博物院",
    "历史": 85.65,
    "稀缺": 87.35,
    "艺术": 93.55,
    "符号": 78.3,
    "加权总分": 87.04
  },
  {
    "rank": 131,
    "no": 153,
    "name": "晋侯夫人组玉佩",
    "era": "西周·约前9世纪-前8世纪",
    "museum": "山西博物院",
    "历史": 86.55,
    "稀缺": 89.6,
    "艺术": 89.65,
    "符号": 76.65,
    "加权总分": 86.94
  },
  {
    "rank": 132,
    "no": 156,
    "name": "镂雕东王公西王母纹玉座屏",
    "era": "东汉·约2世纪",
    "museum": "定州市博物馆",
    "历史": 85.7,
    "稀缺": 89.25,
    "艺术": 92.1,
    "符号": 75.45,
    "加权总分": 86.9
  },
  {
    "rank": 133,
    "no": 140,
    "name": "越窑莲花式托盏",
    "era": "五代·约10世纪",
    "museum": "苏州博物馆",
    "历史": 85.65,
    "稀缺": 87.5,
    "艺术": 93.1,
    "符号": 77.35,
    "加权总分": 86.88
  },
  {
    "rank": 134,
    "no": 101,
    "name": "宋人摹阎立本《步辇图》卷",
    "era": "宋·约10世纪-12世纪",
    "museum": "故宫博物院",
    "历史": 88.4,
    "稀缺": 83.65,
    "艺术": 86.6,
    "符号": 87.95,
    "加权总分": 86.87
  },
  {
    "rank": 135,
    "no": 169,
    "name": "皮胎犀皮漆鎏金铜扣耳杯（2件）",
    "era": "三国·吴·约3世纪",
    "museum": "安徽省文物考古研究所",
    "历史": 85.5,
    "稀缺": 91.8,
    "艺术": 90.85,
    "符号": 72.35,
    "加权总分": 86.81
  },
  {
    "rank": 136,
    "no": 172,
    "name": "河姆渡文化双鸟朝阳纹象牙雕刻器",
    "era": "新石器时代·河姆渡文化（约前5000-前3300年）",
    "museum": "浙江省博物馆",
    "历史": 88.0,
    "稀缺": 89.35,
    "艺术": 85.15,
    "符号": 78.95,
    "加权总分": 86.78
  },
  {
    "rank": 137,
    "no": 120,
    "name": "马家窑文化彩陶贴塑人纹双系壶",
    "era": "新石器时代·马家窑文化（约前3300-前2000年）",
    "museum": "中国国家博物馆",
    "历史": 87.3,
    "稀缺": 90.5,
    "艺术": 86.35,
    "符号": 76.75,
    "加权总分": 86.77
  },
  {
    "rank": 138,
    "no": 90,
    "name": "卫贤《高士图》轴",
    "era": "五代·南唐·约10世纪（卫贤生卒年不详）",
    "museum": "故宫博物院",
    "历史": 85.9,
    "稀缺": 87.45,
    "艺术": 91.9,
    "符号": 77.8,
    "加权总分": 86.77
  },
  {
    "rank": 139,
    "no": 88,
    "name": "胡瓌《卓歇图》卷",
    "era": "五代·约10世纪（胡瓌生卒年不详）",
    "museum": "故宫博物院",
    "历史": 88.15,
    "稀缺": 86.0,
    "艺术": 89.1,
    "符号": 77.05,
    "加权总分": 86.75
  },
  {
    "rank": 140,
    "no": 175,
    "name": "红地对人兽树纹罽袍",
    "era": "汉·约前1世纪-1世纪",
    "museum": "新疆维吾尔自治区文物考古研究所",
    "历史": 86.6,
    "稀缺": 89.65,
    "艺术": 89.15,
    "符号": 75.05,
    "加权总分": 86.71
  },
  {
    "rank": 141,
    "no": 182,
    "name": "曹全碑初拓本（'因'字不损本）",
    "era": "明·约14世纪-15世纪",
    "museum": "上海博物馆",
    "历史": 85.15,
    "稀缺": 90.45,
    "艺术": 89.85,
    "符号": 76.0,
    "加权总分": 86.49
  },
  {
    "rank": 142,
    "no": 146,
    "name": "官窑贯耳尊",
    "era": "北宋·约11世纪-12世纪初",
    "museum": "吉林省博物院",
    "历史": 84.4,
    "稀缺": 89.5,
    "艺术": 92.3,
    "符号": 75.95,
    "加权总分": 86.47
  },
  {
    "rank": 143,
    "no": 128,
    "name": "青釉神兽尊",
    "era": "西晋·约3世纪",
    "museum": "南京博物院",
    "历史": 86.4,
    "稀缺": 86.4,
    "艺术": 90.35,
    "符号": 77.0,
    "加权总分": 86.33
  },
  {
    "rank": 144,
    "no": 164,
    "name": "龟负论语玉烛酒筹鎏金银筒",
    "era": "唐·约9世纪",
    "museum": "镇江博物馆",
    "历史": 85.85,
    "稀缺": 87.95,
    "艺术": 89.85,
    "符号": 76.25,
    "加权总分": 86.25
  },
  {
    "rank": 145,
    "no": 168,
    "name": "彩绘季札挂剑图漆盘",
    "era": "三国·吴·约3世纪",
    "museum": "安徽省文物考古研究所",
    "历史": 85.7,
    "稀缺": 89.45,
    "艺术": 89.75,
    "符号": 72.8,
    "加权总分": 86.16
  },
  {
    "rank": 146,
    "no": 144,
    "name": "钧窑月白釉出戟尊",
    "era": "北宋·约11世纪-12世纪初",
    "museum": "故宫博物院",
    "历史": 83.95,
    "稀缺": 87.25,
    "艺术": 92.35,
    "符号": 79.6,
    "加权总分": 86.12
  },
  {
    "rank": 147,
    "no": 165,
    "name": "彩绘乐舞图鸳鸯形漆盒",
    "era": "战国早期·约前5世纪",
    "museum": "湖北省博物馆",
    "历史": 85.55,
    "稀缺": 86.35,
    "艺术": 91.75,
    "符号": 75.7,
    "加权总分": 86.11
  },
  {
    "rank": 148,
    "no": 108,
    "name": "伯矩鬲",
    "era": "西周早期·约前11世纪-前10世纪",
    "museum": "首都博物馆",
    "历史": 86.0,
    "稀缺": 86.45,
    "艺术": 89.9,
    "符号": 77.15,
    "加权总分": 86.08
  },
  {
    "rank": 149,
    "no": 123,
    "name": "仰韶文化彩陶人形双系瓶",
    "era": "新石器时代·仰韶文化（约前5000-前3000年）",
    "museum": "甘肃省博物馆",
    "历史": 86.25,
    "稀缺": 89.55,
    "艺术": 85.2,
    "符号": 77.4,
    "加权总分": 85.89
  },
  {
    "rank": 150,
    "no": 184,
    "name": "刻开宝藏本《阿惟越致经》（1卷）",
    "era": "北宋·开宝年间（968-976年）",
    "museum": "中国国家图书馆",
    "历史": 90.55,
    "稀缺": 90.35,
    "艺术": 77.1,
    "符号": 73.5,
    "加权总分": 85.84
  },
  {
    "rank": 151,
    "no": 96,
    "name": "李公麟《摹韦偃牧放图》卷",
    "era": "北宋·约11世纪（李公麟1049-1106年）",
    "museum": "故宫博物院",
    "历史": 85.15,
    "稀缺": 84.8,
    "艺术": 92.1,
    "符号": 75.85,
    "加权总分": 85.67
  },
  {
    "rank": 152,
    "no": 141,
    "name": "耀州窑青釉刻花提梁倒流壶",
    "era": "五代·约10世纪",
    "museum": "陕西历史博物馆",
    "历史": 83.5,
    "稀缺": 87.25,
    "艺术": 92.5,
    "符号": 76.15,
    "加权总分": 85.61
  },
  {
    "rank": 153,
    "no": 125,
    "name": "'永安三年'款青釉堆塑谷仓罐",
    "era": "三国·吴·永安三年（260年）",
    "museum": "故宫博物院",
    "历史": 88.2,
    "稀缺": 86.7,
    "艺术": 84.55,
    "符号": 73.4,
    "加权总分": 85.57
  },
  {
    "rank": 154,
    "no": 78,
    "name": "王安石《楞严经旨要》卷",
    "era": "北宋·约11世纪（王安石1021-1086年）",
    "museum": "上海博物馆",
    "历史": 85.45,
    "稀缺": 87.8,
    "艺术": 88.8,
    "符号": 73.75,
    "加权总分": 85.56
  },
  {
    "rank": 155,
    "no": 60,
    "name": "红地云珠日天锦",
    "era": "北朝·约5世纪-6世纪",
    "museum": "青海省博物馆",
    "历史": 87.25,
    "稀缺": 86.85,
    "艺术": 86.15,
    "符号": 73.65,
    "加权总分": 85.56
  },
  {
    "rank": 156,
    "no": 194,
    "name": "秦简《数》",
    "era": "秦·约前3世纪",
    "museum": "湖南大学",
    "历史": 91.8,
    "稀缺": 92.0,
    "艺术": 73.75,
    "符号": 68.25,
    "加权总分": 85.52
  },
  {
    "rank": 157,
    "no": 157,
    "name": "神兽纹玉樽",
    "era": "西晋·约3世纪",
    "museum": "湖南省博物馆",
    "历史": 84.15,
    "稀缺": 88.35,
    "艺术": 91.1,
    "符号": 72.35,
    "加权总分": 85.47
  },
  {
    "rank": 158,
    "no": 166,
    "name": "识文彩绘盝顶长方形漆奁",
    "era": "西汉·约前2世纪",
    "museum": "湖南省博物馆",
    "历史": 84.85,
    "稀缺": 86.45,
    "艺术": 90.6,
    "符号": 73.15,
    "加权总分": 85.31
  },
  {
    "rank": 159,
    "no": 136,
    "name": "越窑青釉褐彩云纹五足炉",
    "era": "唐·天复元年（901年）",
    "museum": "临安博物馆",
    "历史": 84.6,
    "稀缺": 87.2,
    "艺术": 90.4,
    "符号": 72.85,
    "加权总分": 85.3
  },
  {
    "rank": 160,
    "no": 20,
    "name": "朱然墓出土漆木屐",
    "era": "三国·吴·赤乌年间（238-251年）",
    "museum": "马鞍山市三国朱然家族墓地博物馆",
    "历史": 86.95,
    "稀缺": 92.35,
    "艺术": 78.8,
    "符号": 74.65,
    "加权总分": 85.17
  },
  {
    "rank": 161,
    "no": 25,
    "name": "常阳太尊石像",
    "era": "唐·开元年间（713-741年）",
    "museum": "山西省艺术博物馆",
    "历史": 84.55,
    "稀缺": 87.95,
    "艺术": 88.8,
    "符号": 73.05,
    "加权总分": 85.12
  },
  {
    "rank": 162,
    "no": 121,
    "name": "仰韶文化彩陶网纹船形壶",
    "era": "新石器时代·仰韶文化（约前5000-前3000年）",
    "museum": "中国国家博物馆",
    "历史": 85.3,
    "稀缺": 87.3,
    "艺术": 85.15,
    "符号": 78.05,
    "加权总分": 85.0
  },
  {
    "rank": 163,
    "no": 126,
    "name": "'赤乌十四年'款青釉虎子",
    "era": "三国·吴·赤乌十四年（251年）",
    "museum": "中国国家博物馆",
    "历史": 89.1,
    "稀缺": 88.65,
    "艺术": 78.35,
    "符号": 72.8,
    "加权总分": 85.0
  },
  {
    "rank": 164,
    "no": 74,
    "name": "林逋《自书诗》卷",
    "era": "北宋·约11世纪（林逋967-1028年）",
    "museum": "故宫博物院",
    "历史": 83.05,
    "稀缺": 87.4,
    "艺术": 90.75,
    "符号": 74.75,
    "加权总分": 84.91
  },
  {
    "rank": 165,
    "no": 185,
    "name": "北宋刻本《范仲淹文集》（30卷）",
    "era": "北宋·约11世纪",
    "museum": "中国国家图书馆",
    "历史": 88.55,
    "稀缺": 87.8,
    "艺术": 78.3,
    "符号": 74.0,
    "加权总分": 84.67
  },
  {
    "rank": 166,
    "no": 132,
    "name": "青釉凤首龙柄壶",
    "era": "唐·约7世纪-8世纪",
    "museum": "故宫博物院",
    "历史": 83.6,
    "稀缺": 83.85,
    "艺术": 90.85,
    "符号": 76.55,
    "加权总分": 84.55
  },
  {
    "rank": 167,
    "no": 35,
    "name": "摇钱树",
    "era": "东汉（25-220年）",
    "museum": "绵阳市博物馆",
    "历史": 86.15,
    "稀缺": 84.45,
    "艺术": 82.85,
    "符号": 77.45,
    "加权总分": 84.16
  },
  {
    "rank": 168,
    "no": 178,
    "name": "灵鹫纹锦袍",
    "era": "北宋·约10世纪-11世纪",
    "museum": "故宫博物院",
    "历史": 83.5,
    "稀缺": 87.5,
    "艺术": 87.2,
    "符号": 72.5,
    "加权总分": 84.13
  },
  {
    "rank": 169,
    "no": 131,
    "name": "隋白釉龙柄双联传瓶",
    "era": "隋·约6世纪末-7世纪初",
    "museum": "天津博物馆",
    "历史": 82.8,
    "稀缺": 87.65,
    "艺术": 88.7,
    "符号": 71.3,
    "加权总分": 84.06
  },
  {
    "rank": 170,
    "no": 99,
    "name": "马和之《后赤壁赋图》卷",
    "era": "南宋·约12世纪（马和之生卒年不详）",
    "museum": "故宫博物院",
    "历史": 82.35,
    "稀缺": 85.05,
    "艺术": 90.4,
    "符号": 75.05,
    "加权总分": 84.01
  },
  {
    "rank": 171,
    "no": 100,
    "name": "赵伯骕《万松金阙图》卷",
    "era": "南宋·约12世纪（赵伯骕1124-1182年）",
    "museum": "故宫博物院",
    "历史": 82.25,
    "稀缺": 84.7,
    "艺术": 91.5,
    "符号": 72.75,
    "加权总分": 83.9
  },
  {
    "rank": 172,
    "no": 86,
    "name": "王齐翰《勘书图》卷",
    "era": "五代·南唐·约10世纪（王齐翰生卒年不详）",
    "museum": "故宫博物院",
    "历史": 82.9,
    "稀缺": 84.55,
    "艺术": 90.0,
    "符号": 72.3,
    "加权总分": 83.78
  },
  {
    "rank": 173,
    "no": 13,
    "name": "河姆渡出土陶灶",
    "era": "新石器时代·河姆渡文化（约前5000-前3300年）",
    "museum": "浙江省博物馆",
    "历史": 87.7,
    "稀缺": 88.0,
    "艺术": 76.8,
    "符号": 71.75,
    "加权总分": 83.78
  },
  {
    "rank": 174,
    "no": 127,
    "name": "青釉褐彩羽人纹双系壶",
    "era": "三国·吴·约3世纪",
    "museum": "南京市博物馆",
    "历史": 84.15,
    "稀缺": 84.3,
    "艺术": 87.9,
    "符号": 71.4,
    "加权总分": 83.73
  },
  {
    "rank": 175,
    "no": 116,
    "name": "彩绘人物车马镜",
    "era": "西汉·约前2世纪",
    "museum": "西安博物院",
    "历史": 81.45,
    "稀缺": 87.9,
    "艺术": 88.35,
    "符号": 72.3,
    "加权总分": 83.54
  },
  {
    "rank": 176,
    "no": 130,
    "name": "白釉绿彩长颈瓶",
    "era": "北齐·约6世纪",
    "museum": "河南博物院",
    "历史": 86.05,
    "稀缺": 85.1,
    "艺术": 81.95,
    "符号": 68.85,
    "加权总分": 83.21
  },
  {
    "rank": 177,
    "no": 69,
    "name": "国诠书《善见律》卷",
    "era": "唐·约7世纪",
    "museum": "故宫博物院",
    "历史": 82.35,
    "稀缺": 85.4,
    "艺术": 88.7,
    "符号": 69.0,
    "加权总分": 83.11
  },
  {
    "rank": 178,
    "no": 124,
    "name": "大汶口文化彩陶八角星纹豆",
    "era": "新石器时代·大汶口文化（约前4300-前2500年）",
    "museum": "山东博物馆",
    "历史": 83.05,
    "稀缺": 84.1,
    "艺术": 85.35,
    "符号": 74.7,
    "加权总分": 82.96
  },
  {
    "rank": 179,
    "no": 133,
    "name": "鲁山窑黑釉蓝斑腰鼓",
    "era": "唐·约8世纪-9世纪",
    "museum": "故宫博物院",
    "历史": 81.05,
    "稀缺": 86.4,
    "艺术": 88.75,
    "符号": 70.3,
    "加权总分": 82.9
  },
  {
    "rank": 180,
    "no": 163,
    "name": "错金银镶松石狩猎纹铜伞铤",
    "era": "西汉·约前2世纪",
    "museum": "河北省文物研究所",
    "历史": 80.75,
    "稀缺": 84.65,
    "艺术": 91.2,
    "符号": 69.1,
    "加权总分": 82.78
  },
  {
    "rank": 181,
    "no": 152,
    "name": "七孔玉刀",
    "era": "夏·约前21世纪-前16世纪",
    "museum": "洛阳博物馆",
    "历史": 85.1,
    "稀缺": 85.65,
    "艺术": 79.95,
    "符号": 71.6,
    "加权总分": 82.74
  },
  {
    "rank": 182,
    "no": 177,
    "name": "方格兽纹锦",
    "era": "北朝·约5世纪-6世纪",
    "museum": "新疆维吾尔自治区博物馆",
    "历史": 83.1,
    "稀缺": 84.2,
    "艺术": 85.85,
    "符号": 70.6,
    "加权总分": 82.71
  },
  {
    "rank": 183,
    "no": 53,
    "name": "铜屏风构件5件",
    "era": "西汉·约前2世纪",
    "museum": "南越王博物院",
    "历史": 83.95,
    "稀缺": 85.15,
    "艺术": 82.5,
    "符号": 68.9,
    "加权总分": 82.4
  },
  {
    "rank": 184,
    "no": 135,
    "name": "长沙窑青釉褐蓝彩双系罐",
    "era": "唐·约9世纪",
    "museum": "扬州博物馆",
    "历史": 82.1,
    "稀缺": 82.55,
    "艺术": 86.0,
    "符号": 73.0,
    "加权总分": 82.15
  },
  {
    "rank": 185,
    "no": 137,
    "name": "长沙窑青釉褐彩贴花人物纹壶",
    "era": "唐·约9世纪",
    "museum": "湖南省博物馆",
    "历史": 83.05,
    "稀缺": 82.2,
    "艺术": 83.65,
    "符号": 73.15,
    "加权总分": 82.0
  },
  {
    "rank": 186,
    "no": 171,
    "name": "大汶口文化象牙梳",
    "era": "新石器时代·大汶口文化（约前4300-前2500年）",
    "museum": "山东省博物馆",
    "历史": 82.2,
    "稀缺": 87.7,
    "艺术": 80.85,
    "符号": 70.15,
    "加权总分": 81.96
  },
  {
    "rank": 187,
    "no": 173,
    "name": "绿玻璃盖罐",
    "era": "隋·约6世纪末-7世纪初",
    "museum": "中国国家博物馆",
    "历史": 79.35,
    "稀缺": 87.15,
    "艺术": 87.15,
    "符号": 68.35,
    "加权总分": 81.76
  },
  {
    "rank": 188,
    "no": 139,
    "name": "耀州窑摩羯形水盂",
    "era": "五代·约10世纪",
    "museum": "辽宁省博物馆",
    "历史": 79.4,
    "稀缺": 85.5,
    "艺术": 88.25,
    "符号": 67.6,
    "加权总分": 81.57
  },
  {
    "rank": 189,
    "no": 167,
    "name": "黑漆朱绘六博具",
    "era": "西汉·约前2世纪",
    "museum": "湖南省博物馆",
    "历史": 83.55,
    "稀缺": 84.65,
    "艺术": 79.2,
    "符号": 69.5,
    "加权总分": 81.44
  },
  {
    "rank": 190,
    "no": 174,
    "name": "绿玻璃小瓶",
    "era": "隋·约6世纪末-7世纪初",
    "museum": "中国国家博物馆",
    "历史": 79.4,
    "稀缺": 87.65,
    "艺术": 84.4,
    "符号": 67.0,
    "加权总分": 81.16
  },
  {
    "rank": 191,
    "no": 94,
    "name": "梁师闵《芦汀密雪图》卷",
    "era": "北宋·约11世纪（梁师闵生卒年不详）",
    "museum": "故宫博物院",
    "历史": 78.7,
    "稀缺": 83.7,
    "艺术": 88.3,
    "符号": 69.35,
    "加权总分": 81.03
  },
  {
    "rank": 192,
    "no": 95,
    "name": "祁序《江山牧放图》卷",
    "era": "北宋·约11世纪（祁序生卒年不详）",
    "museum": "故宫博物院",
    "历史": 79.5,
    "稀缺": 83.25,
    "艺术": 87.0,
    "符号": 67.85,
    "加权总分": 80.85
  },
  {
    "rank": 193,
    "no": 76,
    "name": "文彦博《三帖卷》",
    "era": "北宋·约11世纪（文彦博1006-1097年）",
    "museum": "故宫博物院",
    "历史": 79.6,
    "稀缺": 83.95,
    "艺术": 85.95,
    "符号": 67.1,
    "加权总分": 80.75
  },
  {
    "rank": 194,
    "no": 147,
    "name": "登封窑珍珠地划花虎豹纹瓶",
    "era": "宋·约11世纪-12世纪",
    "museum": "故宫博物院",
    "历史": 77.4,
    "稀缺": 81.95,
    "艺术": 85.95,
    "符号": 65.75,
    "加权总分": 79.16
  },
  {
    "rank": 195,
    "no": 77,
    "name": "韩琦《行楷信札卷》",
    "era": "北宋·约11世纪（韩琦1008-1075年）",
    "museum": "贵州省博物馆",
    "历史": 76.35,
    "稀缺": 81.5,
    "艺术": 83.05,
    "符号": 62.75,
    "加权总分": 77.65
  }
]